jpsuicide.py
jpsuicide-0.0.4.dist-info/METADATA
jpsuicide-0.0.4.dist-info/WHEEL
jpsuicide-0.0.4.dist-info/entry_points.txt
jpsuicide-0.0.4.dist-info/top_level.txt
jpsuicide-0.0.4.dist-info/RECORD
