Metadata-Version: 2.1
Name: jpsuicide
Version: 0.0.4
Summary: A package for visualizing number of suicides in Japan
Home-page: https://github.com/Reo-Nakadate/jpsuicide
Author: reo nakadate
Author-email: s2022061@stu.musashino-u.ac.jp
License: UNKNOWN
Project-URL: Bug Tracker, https://github.com/Reo-Nakadate/jpsuicide
Platform: UNKNOWN
Classifier: Programming Language :: Python :: 3
Classifier: License :: OSI Approved :: MIT License
Classifier: Operating System :: OS Independent
Requires-Python: >=3.7
